[{"id":1,"first_name":"Lida","last_name":"Gerbl","email":"lgerbl0@wisc.edu","gender":"Bigender","Location":"Sayyān"},
{"id":2,"first_name":"Delila","last_name":"Gislebert","email":"dgislebert1@ifeng.com","gender":"Polygender","Location":"Nagasaki-shi"},
{"id":3,"first_name":"Leonidas","last_name":"Runciman","email":"lrunciman2@bloglovin.com","gender":"Agender","Location":"Rosario de Lerma"},
{"id":4,"first_name":"Chryste","last_name":"Churchard","email":"cchurchard3@so-net.ne.jp","gender":"Male","Location":"Tongzi"},
{"id":5,"first_name":"Giff","last_name":"Murcott","email":"gmurcott4@live.com","gender":"Bigender","Location":"Kimch’aek-si"},
{"id":6,"first_name":"Ly","last_name":"Filler","email":"lfiller5@delicious.com","gender":"Agender","Location":"Sagrada Familia"},
{"id":7,"first_name":"Barbe","last_name":"Kestian","email":"bkestian6@amazon.de","gender":"Non-binary","Location":"Mihara"},
{"id":8,"first_name":"Ernst","last_name":"Jozwiak","email":"ejozwiak7@upenn.edu","gender":"Male","Location":"Vryburg"},
{"id":9,"first_name":"Theodosia","last_name":"LaBastida","email":"tlabastida8@csmonitor.com","gender":"Polygender","Location":"Amiens"},
{"id":10,"first_name":"Jyoti","last_name":"Davisson","email":"jdavisson9@usda.gov","gender":"Agender","Location":"Hamilton"},
{"id":11,"first_name":"Killy","last_name":"Rembaud","email":"krembauda@gmpg.org","gender":"Female","Location":"Lang Suan"},
{"id":12,"first_name":"Chaim","last_name":"Selwood","email":"cselwoodb@e-recht24.de","gender":"Agender","Location":"Sokol"},
{"id":13,"first_name":"Janey","last_name":"Ewells","email":"jewellsc@umich.edu","gender":"Female","Location":"Miracema"},
{"id":14,"first_name":"Carey","last_name":"Uc","email":"cucd@w3.org","gender":"Genderfluid","Location":"Rennes"},
{"id":15,"first_name":"Starla","last_name":"Whear","email":"swheare@twitter.com","gender":"Genderqueer","Location":"Zhukovskiy"},
{"id":16,"first_name":"Haven","last_name":"Philippard","email":"hphilippardf@homestead.com","gender":"Bigender","Location":"Orlovat"},
{"id":17,"first_name":"Angelina","last_name":"Bellinger","email":"abellingerg@comsenz.com","gender":"Genderfluid","Location":"Binucayan"},
{"id":18,"first_name":"Stacia","last_name":"Leathley","email":"sleathleyh@dmoz.org","gender":"Agender","Location":"Murree"},
{"id":19,"first_name":"Goldia","last_name":"Towne","email":"gtownei@hostgator.com","gender":"Agender","Location":"Komsomol’skiy"},
{"id":20,"first_name":"Travers","last_name":"Cawt","email":"tcawtj@gmpg.org","gender":"Polygender","Location":"Tampere"},
{"id":21,"first_name":"Colet","last_name":"Dugget","email":"cduggetk@goo.gl","gender":"Male","Location":"Al Ghayl"},
{"id":22,"first_name":"Killy","last_name":"Eskrick","email":"keskrickl@deviantart.com","gender":"Genderfluid","Location":"Beitai"},
{"id":23,"first_name":"Pembroke","last_name":"Tabart","email":"ptabartm@live.com","gender":"Genderfluid","Location":"Candelaria"},
{"id":24,"first_name":"Sigrid","last_name":"Alibone","email":"salibonen@multiply.com","gender":"Bigender","Location":"Hengjing"},
{"id":25,"first_name":"Simone","last_name":"Fissenden","email":"sfissendeno@booking.com","gender":"Bigender","Location":"Tenri"},
{"id":26,"first_name":"Arron","last_name":"Deboick","email":"adeboickp@yale.edu","gender":"Agender","Location":"Pozo Hondo"},
{"id":27,"first_name":"Quintus","last_name":"Pedden","email":"qpeddenq@upenn.edu","gender":"Genderfluid","Location":"Lille"},
{"id":28,"first_name":"Therine","last_name":"Welchman","email":"twelchmanr@japanpost.jp","gender":"Agender","Location":"Gonayiv"},
{"id":29,"first_name":"Tyson","last_name":"Lowrie","email":"tlowries@opensource.org","gender":"Polygender","Location":"Phong Điền"},
{"id":30,"first_name":"Derril","last_name":"Ropartz","email":"dropartzt@blogs.com","gender":"Female","Location":"Pýrgos"},
{"id":31,"first_name":"Charlena","last_name":"Gergely","email":"cgergelyu@economist.com","gender":"Non-binary","Location":"Alegria"},
{"id":32,"first_name":"Elizabeth","last_name":"Simeons","email":"esimeonsv@soundcloud.com","gender":"Female","Location":"Jiuheyuan"},
{"id":33,"first_name":"Baxie","last_name":"Kloser","email":"bkloserw@pinterest.com","gender":"Male","Location":"Medellin"},
{"id":34,"first_name":"Rozele","last_name":"Eake","email":"reakex@dailymotion.com","gender":"Bigender","Location":"Kobylanka"},
{"id":35,"first_name":"Byram","last_name":"Flay","email":"bflayy@usa.gov","gender":"Female","Location":"Guradog"},
{"id":36,"first_name":"Shaun","last_name":"Screwton","email":"sscrewtonz@1und1.de","gender":"Polygender","Location":"Mernek"},
{"id":37,"first_name":"Emmett","last_name":"Antliff","email":"eantliff10@nih.gov","gender":"Agender","Location":"Marondera"},
{"id":38,"first_name":"Winni","last_name":"Leif","email":"wleif11@wikimedia.org","gender":"Genderfluid","Location":"Beaufort"},
{"id":39,"first_name":"Alla","last_name":"Bonar","email":"abonar12@cdc.gov","gender":"Bigender","Location":"Boleszkowice"},
{"id":40,"first_name":"Sherwynd","last_name":"Reihill","email":"sreihill13@instagram.com","gender":"Agender","Location":"Yueshan"},
{"id":41,"first_name":"Willi","last_name":"Armal","email":"warmal14@boston.com","gender":"Genderqueer","Location":"Sukojember"},
{"id":42,"first_name":"Gram","last_name":"Bentham3","email":"gbentham15@opera.com","gender":"Male","Location":"Goranboy"},
{"id":43,"first_name":"Marti","last_name":"Baudry","email":"mbaudry16@de.vu","gender":"Bigender","Location":"Guanaja"},
{"id":44,"first_name":"Nanette","last_name":"Grishinov","email":"ngrishinov17@nps.gov","gender":"Genderqueer","Location":"Vargön"},
{"id":45,"first_name":"Seline","last_name":"Boyat","email":"sboyat18@jigsy.com","gender":"Polygender","Location":"Miribel"},
{"id":46,"first_name":"Cami","last_name":"Serotsky","email":"cserotsky19@mozilla.com","gender":"Non-binary","Location":"Kunčina"},
{"id":47,"first_name":"Maud","last_name":"Le Prevost","email":"mleprevost1a@columbia.edu","gender":"Male","Location":"Bāgh-e Maīdān"},
{"id":48,"first_name":"Maxine","last_name":"Nowick","email":"mnowick1b@networksolutions.com","gender":"Genderqueer","Location":"Montréal-Est"},
{"id":49,"first_name":"Di","last_name":"Lampke","email":"dlampke1c@ted.com","gender":"Non-binary","Location":"Jutiapa"},
{"id":50,"first_name":"Hilde","last_name":"Farrar","email":"hfarrar1d@godaddy.com","gender":"Genderqueer","Location":"Krebetkrajan"},
{"id":51,"first_name":"Tonye","last_name":"McNerlin","email":"tmcnerlin1e@cdc.gov","gender":"Male","Location":"Rostov-na-Donu"},
{"id":52,"first_name":"Laura","last_name":"Lortzing","email":"llortzing1f@slashdot.org","gender":"Non-binary","Location":"Santa Ana"},
{"id":53,"first_name":"Selina","last_name":"Files","email":"sfiles1g@wufoo.com","gender":"Genderqueer","Location":"Shitang"},
{"id":54,"first_name":"Cookie","last_name":"Jambrozek","email":"cjambrozek1h@wikipedia.org","gender":"Genderqueer","Location":"Virovitica"},
{"id":55,"first_name":"Anissa","last_name":"Bucklee","email":"abucklee1i@google.cn","gender":"Female","Location":"Selajambe Satu"},
{"id":56,"first_name":"Judd","last_name":"Vero","email":"jvero1j@friendfeed.com","gender":"Genderfluid","Location":"Dan Sadau"},
{"id":57,"first_name":"Shanon","last_name":"Waud","email":"swaud1k@sogou.com","gender":"Non-binary","Location":"Sindangraja"},
{"id":58,"first_name":"Dyane","last_name":"Leslie","email":"dleslie1l@webeden.co.uk","gender":"Polygender","Location":"Caihua"},
{"id":59,"first_name":"Olin","last_name":"Gotthard","email":"ogotthard1m@fotki.com","gender":"Agender","Location":"Cana Chapetón"},
{"id":60,"first_name":"Phylys","last_name":"Clutram","email":"pclutram1n@vk.com","gender":"Bigender","Location":"Hua Hin"},
{"id":61,"first_name":"Clark","last_name":"Finn","email":"cfinn1o@engadget.com","gender":"Polygender","Location":"Liusi"},
{"id":62,"first_name":"Ilyssa","last_name":"Lamswood","email":"ilamswood1p@bloglovin.com","gender":"Agender","Location":"Dahuang"},
{"id":63,"first_name":"Brenden","last_name":"Thrower","email":"bthrower1q@163.com","gender":"Non-binary","Location":"Lebak Timur"},
{"id":64,"first_name":"Flora","last_name":"Vinas","email":"fvinas1r@vk.com","gender":"Genderfluid","Location":"Douane"},
{"id":65,"first_name":"Micky","last_name":"Paik","email":"mpaik1s@ucoz.ru","gender":"Bigender","Location":"Palanit"},
{"id":66,"first_name":"Cherish","last_name":"Venney","email":"cvenney1t@whitehouse.gov","gender":"Female","Location":"Lycksele"},
{"id":67,"first_name":"Immanuel","last_name":"Foulkes","email":"ifoulkes1u@techcrunch.com","gender":"Bigender","Location":"Nierumai"},
{"id":68,"first_name":"Abigael","last_name":"Peachman","email":"apeachman1v@examiner.com","gender":"Non-binary","Location":"Pisangkemeng"},
{"id":69,"first_name":"Xaviera","last_name":"Mirams","email":"xmirams1w@google.fr","gender":"Genderqueer","Location":"Joconal"},
{"id":70,"first_name":"Brana","last_name":"Cant","email":"bcant1x@privacy.gov.au","gender":"Genderfluid","Location":"Olleros"},
{"id":71,"first_name":"Margeaux","last_name":"Bowe","email":"mbowe1y@biblegateway.com","gender":"Non-binary","Location":"Roshnik"},
{"id":72,"first_name":"Aurthur","last_name":"Bamell","email":"abamell1z@purevolume.com","gender":"Agender","Location":"Shah Alam"},
{"id":73,"first_name":"Dermot","last_name":"Couth","email":"dcouth20@home.pl","gender":"Genderqueer","Location":"Baykit"},
{"id":74,"first_name":"Thibaut","last_name":"Bosley","email":"tbosley21@bloglovin.com","gender":"Genderqueer","Location":"Alcanena"},
{"id":75,"first_name":"Christy","last_name":"Castles","email":"ccastles22@sphinn.com","gender":"Genderfluid","Location":"Taifu"},
{"id":76,"first_name":"Shellie","last_name":"De Vere","email":"sdevere23@linkedin.com","gender":"Polygender","Location":"Sahavato"},
{"id":77,"first_name":"Terry","last_name":"Wayland","email":"twayland24@ifeng.com","gender":"Genderqueer","Location":"Bieliny"},
{"id":78,"first_name":"Peggy","last_name":"Tiptaft","email":"ptiptaft25@cam.ac.uk","gender":"Non-binary","Location":"Maubin"},
{"id":79,"first_name":"Euell","last_name":"Skeleton","email":"eskeleton26@thetimes.co.uk","gender":"Agender","Location":"Wajak"},
{"id":80,"first_name":"Onofredo","last_name":"Baglan","email":"obaglan27@jimdo.com","gender":"Polygender","Location":"Gävle"},
{"id":81,"first_name":"Ronald","last_name":"Merrill","email":"rmerrill28@youku.com","gender":"Agender","Location":"Louisville"},
{"id":82,"first_name":"Wanda","last_name":"McGraith","email":"wmcgraith29@theglobeandmail.com","gender":"Polygender","Location":"Viana"},
{"id":83,"first_name":"Paloma","last_name":"Pleat","email":"ppleat2a@comcast.net","gender":"Non-binary","Location":"Fovissste"},
{"id":84,"first_name":"Arlen","last_name":"Keeling","email":"akeeling2b@wufoo.com","gender":"Male","Location":"San Pedro"},
{"id":85,"first_name":"Lemmie","last_name":"Boulden","email":"lboulden2c@statcounter.com","gender":"Genderqueer","Location":"Na Kae"},
{"id":86,"first_name":"Charlotta","last_name":"Duguid","email":"cduguid2d@studiopress.com","gender":"Non-binary","Location":"Xinji"},
{"id":87,"first_name":"Prudence","last_name":"Parton","email":"pparton2e@utexas.edu","gender":"Bigender","Location":"Polovinnoye"},
{"id":88,"first_name":"Algernon","last_name":"Artist","email":"aartist2f@wsj.com","gender":"Genderfluid","Location":"Massaguet"},
{"id":89,"first_name":"Reggie","last_name":"Enticknap","email":"renticknap2g@skyrock.com","gender":"Polygender","Location":"Guanabacoa"},
{"id":90,"first_name":"Hazel","last_name":"Agdahl","email":"hagdahl2h@macromedia.com","gender":"Polygender","Location":"Kota Kinabalu"},
{"id":91,"first_name":"Viviyan","last_name":"Wandrach","email":"vwandrach2i@google.cn","gender":"Bigender","Location":"Stalbe"},
{"id":92,"first_name":"Nichole","last_name":"Hoyland","email":"nhoyland2j@irs.gov","gender":"Male","Location":"Stockholm"},
{"id":93,"first_name":"See","last_name":"Ralfe","email":"sralfe2k@pinterest.com","gender":"Male","Location":"Hegarmulya"},
{"id":94,"first_name":"Shana","last_name":"Wardhough","email":"swardhough2l@surveymonkey.com","gender":"Bigender","Location":"Kasturi"},
{"id":95,"first_name":"Colan","last_name":"Dahlbom","email":"cdahlbom2m@si.edu","gender":"Genderqueer","Location":"Dubreuil"},
{"id":96,"first_name":"Kiri","last_name":"Denniston","email":"kdenniston2n@globo.com","gender":"Non-binary","Location":"Talon"},
{"id":97,"first_name":"Osborne","last_name":"Priddey","email":"opriddey2o@reference.com","gender":"Male","Location":"Temirtau"},
{"id":98,"first_name":"Trumaine","last_name":"Axcel","email":"taxcel2p@squarespace.com","gender":"Genderqueer","Location":"Chang’an"},
{"id":99,"first_name":"Teodor","last_name":"Waggett","email":"twaggett2q@google.com","gender":"Bigender","Location":"Severomorsk"},
{"id":100,"first_name":"Glory","last_name":"Norquay","email":"gnorquay2r@ask.com","gender":"Non-binary","Location":"Pindamonhangaba"}]